LICENSE
MANIFEST.in
README.md
setup.cfg
setup.py
OctoPrint_HeaderAnnouncements.egg-info/PKG-INFO
OctoPrint_HeaderAnnouncements.egg-info/SOURCES.txt
OctoPrint_HeaderAnnouncements.egg-info/dependency_links.txt
OctoPrint_HeaderAnnouncements.egg-info/entry_points.txt
OctoPrint_HeaderAnnouncements.egg-info/not-zip-safe
OctoPrint_HeaderAnnouncements.egg-info/requires.txt
OctoPrint_HeaderAnnouncements.egg-info/top_level.txt
octoprint_HeaderAnnouncements/__init__.py
octoprint_HeaderAnnouncements/common/SettingsKeys.py
octoprint_HeaderAnnouncements/common/__init__.py
octoprint_HeaderAnnouncements/static/css/HeaderAnnouncements.css
octoprint_HeaderAnnouncements/static/js/HeaderAnnouncements.js
octoprint_HeaderAnnouncements/static/less/HeaderAnnouncements.less
octoprint_HeaderAnnouncements/templates/HeaderAnnouncements.jinja2
octoprint_HeaderAnnouncements/templates/HeaderAnnouncements_settings.jinja2